[
  {
    "date": "2026-06-01",
    "company": "Amazon India",
    "title": "Amazon India Quick-Commerce Scale-Up: direct sourcing from farmers, fulfillment centers to compete with Blinkit",
    "url": "",
    "key": "amazon blinkit centers commerce compete direct farmers from fulfillment india quick scale sourcing with"
  },
  {
    "date": "2026-06-01",
    "company": "Flipkart",
    "title": "Flipkart launches GRWM Get Ready With Me season sale fashion discounts Kinnect",
    "url": "",
    "key": "discounts fashion flipkart grwm kinnect launches ready sale season with"
  },
  {
    "date": "2026-06-01",
    "company": "Myntra",
    "title": "Myntra RCB IPL win moment marketing social media campaign",
    "url": "",
    "key": "campaign marketing media moment myntra social"
  },
  {
    "date": "2026-06-01",
    "company": "PharmEasy",
    "title": "PharmEasy launches AI-powered at-home rehabilitation platform pain management",
    "url": "",
    "key": "home launches management pain pharmeasy platform powered rehabilitation"
  },
  {
    "date": "2026-06-01",
    "company": "Blinkit",
    "title": "FSSAI quality notice to Blinkit over bad-quality curd complaints Action Taken Report",
    "url": "",
    "key": "action blinkit complaints curd fssai notice over quality report taken"
  },
  {
    "date": "2026-06-01",
    "company": "Blinkit",
    "title": "Deepinder Goyal says Blinkit commands 50% of India quick-commerce market, better positioned than Amazon",
    "url": "",
    "key": "amazon better blinkit commands commerce deepinder goyal india market positioned quick says than"
  },
  {
    "date": "2026-06-01",
    "company": "Scapia",
    "title": "Scapia closes $63M Series C led by General Catalyst at $500M valuation",
    "url": "",
    "key": "500m catalyst closes general scapia series valuation"
  },
  {
    "date": "2026-06-01",
    "company": "India China Relations",
    "title": "India and China hold constructive 35th WMCC meeting on Eastern Ladakh border situation",
    "url": "",
    "key": "35th border china constructive eastern hold india ladakh meeting situation wmcc"
  },
  {
    "date": "2026-05-31",
    "company": "Amazon India",
    "title": "Amazon quick-commerce entry accelerates: direct sourcing from farmers, collection and fulfilment centres vs Blinkit",
    "url": "",
    "key": "accelerates amazon blinkit centres collection commerce direct entry farmers from fulfilment quick sourcing"
  },
  {
    "date": "2026-05-31",
    "company": "Amazon India",
    "title": "Amazon India devices business is blueprint for global expansion (Echo, Alexa)",
    "url": "",
    "key": "alexa amazon blueprint business devices echo expansion global india"
  },
  {
    "date": "2026-05-31",
    "company": "Flipkart",
    "title": "Flipkart GRWM Fashion Sale targets Gen Z with humour, internet culture, music-led storytelling",
    "url": "",
    "key": "culture fashion flipkart grwm humour internet music sale storytelling targets with"
  },
  {
    "date": "2026-05-31",
    "company": "PharmEasy",
    "title": "PharmEasy launches AI-powered at-home rehabilitation and guided pain management services",
    "url": "",
    "key": "guided home launches management pain pharmeasy powered rehabilitation services"
  },
  {
    "date": "2026-05-31",
    "company": "Nike India",
    "title": "Nike.in operations transitioned to Nykaa partnership; Westbury distribution continues",
    "url": "",
    "key": "continues distribution nike nykaa operations partnership transitioned westbury"
  },
  {
    "date": "2026-05-31",
    "company": "Aditya Birla Group",
    "title": "Aditya Birla Fashion appoints Suchit Kakar as Senior Manager for Galeries Lafayette luxury retail",
    "url": "",
    "key": "aditya appoints birla fashion galeries kakar lafayette luxury manager retail senior suchit"
  },
  {
    "date": "2026-05-31",
    "company": "Cars24",
    "title": "Himanshu Ratnoo, former CARS24 India CEO, joins EMotorad as co-founder in electric mobility",
    "url": "",
    "key": "cars24 electric emotorad former founder himanshu india joins mobility ratnoo"
  },
  {
    "date": "2026-05-31",
    "company": "Smytten",
    "title": "Humuss Beauty skincare brand now distributed across Smytten, Blinkit, Amazon, Flipkart",
    "url": "",
    "key": "across amazon beauty blinkit brand distributed flipkart humuss skincare smytten"
  },
  {
    "date": "2026-05-30",
    "company": "Amazon India",
    "title": "Supreme Court quashes Rs 202 Cr CCI penalty on Amazon in Future Coupons case",
    "url": "",
    "key": "amazon case coupons court future penalty quashes supreme"
  },
  {
    "date": "2026-05-30",
    "company": "Amazon India",
    "title": "Amazon India signs MoUs to support 500 women entrepreneurs under Prayatna (menstrual hygiene)",
    "url": "",
    "key": "amazon entrepreneurs hygiene india menstrual mous prayatna signs support under women"
  },
  {
    "date": "2026-05-30",
    "company": "Amazon India",
    "title": "Amazon launches Echo Dot Max and Echo Studio smart speakers in India",
    "url": "",
    "key": "amazon echo india launches smart speakers studio"
  },
  {
    "date": "2026-05-30",
    "company": "Flipkart",
    "title": "Flipkart partners India Post for last-mile delivery; asset-light logistics shift",
    "url": "",
    "key": "asset delivery flipkart india last light logistics mile partners post shift"
  },
  {
    "date": "2026-05-30",
    "company": "Myntra",
    "title": "Myntra 24th End of Reason Sale (EORS) launches with 6 million styles, 5,000 new brand debuts",
    "url": "",
    "key": "24th brand debuts eors launches million myntra reason sale styles with"
  },
  {
    "date": "2026-05-30",
    "company": "Blinkit",
    "title": "28 BLACK premium German energy drink launched on Blinkit",
    "url": "",
    "key": "black blinkit drink energy german launched premium"
  }
]